paella/__init__.py
paella/paella.py
paella_auth-0.5.0.dist-info/METADATA
paella_auth-0.5.0.dist-info/WHEEL
paella_auth-0.5.0.dist-info/licenses/LICENSE
paella_auth-0.5.0.dist-info/RECORD
