Metadata-Version: 2.1
Name: paella_auth
Version: 0.5.0
Summary: Simple, extensible Asynchronous Authnz library
Author-Email: Stephen Sadowski <stephen.sadowski@sjsadowski.com>
License: MIT
Requires-Python: >=3.11
Requires-Dist: pyjwt[crypto]>=2.8.0
